{
  "catalogs": [
    {
      "links": [
        {
          "href": "https://circulation-beta.ellibs.com/groups/",
          "type": "application/atom+xml;profile=opds-catalog;kind=acquisition",
          "rel": "http://opds-spec.org/catalog"
        },
        {
          "href": "https://circulation-beta.ellibs.com/groups/",
          "rel": "start"
        },
        {
          "href": "https://circulation-beta.ellibs.com/groups/",
          "rel": "self"
        },
        {
          "href": "https://circulation-beta.ellibs.com/authentication_document",
          "type": "application/vnd.opds.authentication.v1.0+json"
        },
        {
          "href": "https://openebooks.net/",
          "type": "text/html",
          "rel": "alternate"
        },
        {
          "href": "https://https://e-kirjasto-playground.epaper.fi/",
          "rel": "digital_magazines"
        },
        {
            "href": "https://librarysimplified.org/licenses/",
            "type": "text/html",
            "rel": "license"
        },
        {
          "href": "https://circulation-beta.ellibs.com/palaute",
          "rel": "help"
        }
      ],
      "metadata": {
        "updated": "2024-04-15T07:24:51Z",
        "description": "E-kirjaston kokoelma",
        "id": "urn:uuid:2fcb96c3-b639-4b12-ab50-4172a0410a07",
        "title": "E-kirjaston kokoelma"
      }
    }
  ],
  "links": [
      {
        "href": "https://circulation-beta.ellibs.com/",
        "type": "application/opds+json",
        "rel": "self"
      }
  ],
  "metadata": {
    "title": "E-kirjasto"
  }
}
